{"data": [{"created_at": "2012-10-16T12:49:45.000Z", "id": "884378714", "name": "SMTOWN", "username": "SMTOWNGLOBAL"}, {"created_at": "2011-08-01T14:58:08.000Z", "id": "346604946", "name": "CUBE ENTERTAINMENT", "username": "cubeunited"}, {"created_at": "2013-09-03T19:46:16.000Z", "id": "1726478174", "name": "\uc784\ud604\uc2dd", "username": "BTOB_IMHYUNSIK"}, {"created_at": "2021-02-05T11:30:42.000Z", "id": "1357652667279896577", "name": "\ube44\ud22c\ube44 \uc190\ubbfc\uc218\ud15c \uc815\ubcf4", "username": "btob_TMI_"}, {"created_at": "2012-04-02T14:41:37.000Z", "id": "543462047", "name": "BTOB\u00b7\ube44\ud22c\ube44", "username": "OFFICIALBTOB"}, {"created_at": "2019-05-22T03:31:18.000Z", "id": "1131039806765522944", "name": "\uc774\uc601\uc9c0", "username": "dokgodieinsaeng"}], "meta": {"result_count": 6}}