{"data": [{"created_at": "2021-08-22T17:26:31.000Z", "id": "1429495170957922304", "name": "\ud83c\udf6d CANDY SUGA | \uce94\ub514\uc288\uac00 \ud83c\udf6d", "username": "candySUGA309"}, {"created_at": "2021-05-10T16:10:06.000Z", "id": "1391787610868047877", "name": "\uc9c4", "username": "BTS_twt_SJlN"}, {"created_at": "2021-06-13T14:49:13.000Z", "id": "1404088307923906564", "name": "jhope", "username": "u_army_hobi"}, {"created_at": "2021-11-25T05:57:17.000Z", "id": "1463748517982347265", "name": "THV", "username": "BTSTaehyungTHV"}, {"created_at": "2021-05-09T05:15:29.000Z", "id": "1391260456765906949", "name": "JIMIN", "username": "BTS_twt_JIMINP"}, {"created_at": "2021-02-21T02:34:04.000Z", "id": "1363315994878300169", "name": "JHOPE", "username": "uuamyhope"}, {"created_at": "2021-10-14T12:29:52.000Z", "id": "1448627067856179203", "name": "Kep1er", "username": "official_kep1er"}, {"created_at": "2017-03-13T06:33:00.000Z", "id": "841175241233641472", "name": "\uc804\uc815\uad6d BTS JUNGKOOK", "username": "BTS_twt_JKG"}, {"created_at": "2013-05-15T04:13:34.000Z", "id": "1429480158", "name": "BamBam", "username": "BamBam1A"}, {"created_at": "2010-03-23T09:09:53.000Z", "id": "125603760", "name": "Davidsiwonchoi.eth", "username": "siwonchoi"}, {"created_at": "2019-01-10T03:07:41.000Z", "id": "1083198663424237569", "name": "TXT OFFICIAL", "username": "TXT_bighit"}, {"created_at": "2012-10-16T12:49:45.000Z", "id": "884378714", "name": "SMTOWN", "username": "SMTOWNGLOBAL"}, {"created_at": "2018-05-26T03:18:58.000Z", "id": "1000214682530074624", "name": "Baekhyun_EXO", "username": "B_hundred_Hyun"}, {"created_at": "2015-02-11T12:25:12.000Z", "id": "3030158859", "name": "\ubaac\uc2a4\ud0c0\uc5d1\uc2a4_MONSTA X", "username": "OfficialMonstaX"}, {"created_at": "2011-11-09T02:41:52.000Z", "id": "408177579", "name": "YG FAMILY", "username": "ygent_official"}, {"created_at": "2012-11-19T06:57:38.000Z", "id": "956888370", "name": "\uc138\ube10\ud2f4(SEVENTEEN)", "username": "pledis_17"}, {"created_at": "2016-01-04T12:39:29.000Z", "id": "4708707631", "name": "V", "username": "BTS_twt_THE"}, {"created_at": "2018-11-05T06:11:32.000Z", "id": "1059327333532749824", "name": "TOMORROW X TOGETHER", "username": "TXT_members"}, {"created_at": "2017-05-02T06:46:15.000Z", "id": "859297966581891072", "name": "Stray Kids", "username": "Stray_Kids"}, {"created_at": "2020-09-15T15:37:25.000Z", "id": "1305893393835290624", "name": "ENHYPEN", "username": "ENHYPEN_members"}, {"created_at": "2017-06-09T08:20:31.000Z", "id": "873092428755894272", "name": "Red Velvet", "username": "RVsmtown"}, {"created_at": "2020-03-19T13:15:22.000Z", "id": "1240627844868268033", "name": "TREASURE", "username": "treasuremembers"}, {"created_at": "2018-11-14T05:31:22.000Z", "id": "1062578718214770688", "name": "ITZY", "username": "ITZYofficial"}, {"created_at": "2021-03-17T04:57:28.000Z", "id": "1372049374436421635", "name": "Jin", "username": "BTS_twtt_JIN"}, {"created_at": "2021-05-12T02:15:24.000Z", "id": "1392302226782052355", "name": "NMIXX", "username": "NMIXX_official"}, {"created_at": "2015-04-02T05:43:40.000Z", "id": "3129056526", "name": "TWICE", "username": "JYPETWICE"}, {"created_at": "2017-06-09T09:51:57.000Z", "id": "873115441303924736", "name": "EXO", "username": "weareoneEXO"}, {"created_at": "2017-06-23T10:53:32.000Z", "id": "878204370403250176", "name": "BLACKPINK GLOBAL BLINK", "username": "ygofficialblink"}, {"created_at": "2020-06-19T05:32:29.000Z", "id": "1273850774380883975", "name": "BLACKPINKOFFICIAL", "username": "BLACKPINK"}, {"created_at": "2020-06-03T02:54:15.000Z", "id": "1268013027997048838", "name": "TinyTAN_official", "username": "TinyTANofficial"}, {"created_at": "2017-08-07T12:34:02.000Z", "id": "894537112225067008", "name": "BT21", "username": "BT21_"}, {"created_at": "2010-07-20T14:40:33.000Z", "id": "168683422", "name": "BIGHIT MUSIC", "username": "BIGHIT_MUSIC"}, {"created_at": "2016-02-12T16:26:21.000Z", "id": "4898053448", "name": "JIMIN of BTS", "username": "BTS_twt_JIMINPK"}, {"created_at": "2021-02-17T04:55:10.000Z", "id": "1361901840556728320", "name": "j.m", "username": "BTS_twt_JIMlNIE"}, {"created_at": "2021-02-13T13:37:47.000Z", "id": "1360583919263911937", "name": "RM", "username": "BTS_twt_JOONIE"}, {"created_at": "2021-03-26T09:08:18.000Z", "id": "1375373968673099778", "name": "SUGA of BTS \ubbfc\uc724\uae30", "username": "BTS_twt_SUGAMYG"}, {"created_at": "2021-06-18T15:09:57.000Z", "id": "1405905563104342020", "name": "SUGA", "username": "agustd_sugamyg"}, {"created_at": "2021-02-16T03:23:20.000Z", "id": "1361516455280320512", "name": "agustd", "username": "BTS_twt_MlNSUGA"}, {"created_at": "2020-04-07T08:41:10.000Z", "id": "1247444244014313472", "name": "V", "username": "BTS_twt_VKTH"}, {"created_at": "2021-02-13T13:15:19.000Z", "id": "1360578258752794629", "name": "jhope", "username": "BTS_twt_JHOBI"}, {"created_at": "2019-12-21T00:08:43.000Z", "id": "1208177379346010112", "name": "Jungkook", "username": "BTS_twt_JUNGKK"}, {"created_at": "2021-03-30T23:42:55.000Z", "id": "1377043537452146688", "name": "HYBE OFFICIAL", "username": "HYBEOFFICIALtwt"}, {"created_at": "2013-05-07T09:13:05.000Z", "id": "1409798257", "name": "BTS_official", "username": "bts_bighit"}, {"created_at": "2011-07-14T06:32:56.000Z", "id": "335141638", "name": "\ubc29\ud0c4\uc18c\ub144\ub2e8", "username": "BTS_twt"}], "meta": {"result_count": 44}}